Metadata-Version: 1.0
Name: satyr
Version: 0.1.3
Summary: Extensible Python Framework for Apache Mesos
Home-page: http://github.com/lensacom/satyr
Author: Krisztián Szűcs
Author-email: krisztian.szucs@lensa.com
License: Apache License, Version 2.0
Keywords: mesos framework multiprocessing
Platform: UNKNOWN
